Workbook

Sheet Instructions
A1: Oasis Salon Feasibility — Excel Workbook Guide
A3: 📋 HOW THIS WORKBOOK IS STRUCTURED
A5: • Country sheet: Edit tax rates and monthly staff salaries (in USD) per country.
A6: • Cities sheet: Edit all raw inputs per city (yellow cells only):
A7: - Space (sq ft), sessions/day, working days, ticket price, COGS %
A8: - Rent, fitout cost, equipment cost, other CAPEX, deposit months
A9: - Latitude, Longitude, and Underserved Gap % (for map visualization)
A10: - Biz Reg Fee (one-time license fee) and Admin & SW (monthly admin overhead)
A11: - Year 1 and Year 2 utilisation targets
A12: • Model sheet: All calculations. Do NOT edit directly. Reads from Cities + Country.
A14: ⚙️ KEY FORMULAS
A16: Styling Stations = IF(sqft ≤ 750 → 3, sqft ≤ 850 → 4, else 5)
... A49: • Equipment depreciation over 5 years reduces taxable income (tax shield) and is added back for cash flow payback.

Sheet Country
A1: Country Parameters — Salon Financial Model
A2: ✏ Edit these cells to update assumptions. Run excel_to_json.py after any change.
A3: Country Code | B3: Country Name | C3: Corp. Tax Rate | D3: Currency | E3: Senior Stylist (USD/mo) | F3: Junior Stylist (USD/mo) | G3: Assistant (USD/mo) | H3: Manager (USD/mo)
A4: AU | B4: Australia | C4: 0.3 | D4: AUD | E4: 4225 | F4: 2800 | G4: 2470 | H4: 4550
A5: JP | B5: Japan | C5: 0.3 | D5: JPY | E5: 2345 | F5: 1474 | G5: 1474 | H5: 3015
A6: KR | B6: South Korea | C6: 0.22 | D6: KRW | E6: 2044 | F6: 1314 | G6: 1314 | H6: 2555
A7: SG | B7: Singapore | C7: 0.17 | D7: SGD | E7: 3330 | F7: 2480 | G7: 1850 | H7: 4440
A8: HK | B8: Hong Kong | C8: 0.165 | D8: HKD | E8: 2432 | F8: 1792 | G8: 1664 | H8: 3072
A9: MC | B9: Macau | C9: 0.12 | D9: HKD | E9: 2304 | F9: 1536 | G9: 1536 | H9: 2816
A10: TW | B10: Taiwan | C10: 0.2 | D10: NTD | E10: 1705 | F10: 992 | G10: 992 | H10: 2170
A11: MY | B11: Malaysia | C11: 0.24 | D11: MYR | E11: 990 | F11: 660 | G11: 484 | H11: 1320
A12: VN | B12: Vietnam | C12: 0.2 | D12: VND | E12: 800 | F12: 500 | G12: 420 | H12: 1100
A13: TH | B13: Thailand | C13: 0.2 | D13: THB | E13: 1305 | F13: 870 | G13: 638 | H13: 1740
A14: AE | B14: UAE / Dubai | C14: 0.09 | D14: AED | E14: 2720 | F14: 1904 | G14: 1632 | H14: 3808
A16: 💡 Country lookup: These rows are referenced by VLOOKUP in the Cities sheet. Do not change the Country Code column (column A). Add new countries at the bottom.

Sheet Cities
A1: Oasis Salon — City Input Parameters
A2: ✏ YELLOW = editable inputs. BLUE (Model sheet) = auto-calculated. After editing, run: python excel_to_json.py
A3: IDENTITY | E3: SPACE & TIME | H3: PRICING | J3: COSTS & CAPEX | O3: UTILISATION | Q3: GEOGRAPHY | T3: BUSINESS FEES & ADMIN
A4: City Name | B4: URL | C4: Region | D4: Country Code | E4: Space (sq ft) | F4: Sessions/ Station/Day | G4: Working Days/Month | H4: Ticket (USD) | I4: COGS % | J4: Rent (USD/mo) | K4: Fitout (USD) | L4: Equipment (USD) | M4: Other CAPEX (USD) | N4: Deposit Months | O4: Util Y1 (%) | P4: Util Y2 (%) | Q4: Latitude | R4: Longitude | S4: Underserved Gap % | T4: Biz Reg Fee (USD) | U4: Admin & SW (USD/mo)
A5: Ho Chi Minh | B5: hcmc.html | C5: Vietnam | D5: VN | E5: 800 | F5: 3 | G5: 26 | H5: 95 | I5: 0.1 | J5: 3000 | K5: 20000 | L5: 20000 | M5: 9000 | N5: 3 | O5: 0.65 | P5: 0.75 | Q5: 10.776 | R5: 106.701 | S5: 65 | T5: 6500 | U5: 200
A6: Hanoi | B6: hanoi.html | C6: Vietnam | D6: VN | E6: 800 | F6: 3 | G6: 26 | H6: 95 | I6: 0.1 | J6: 2200 | K6: 18000 | L6: 18000 | M6: 7600 | N6: 3 | O6: 0.65 | P6: 0.75 | Q6: 21.028 | R6: 105.852 | S6: 55 | T6: 6500 | U6: 200
A7: Da Nang | B7: danang.html | C7: Vietnam | D7: VN | E7: 800 | F7: 4 | G7: 26 | H7: 55 | I7: 0.1 | J7: 800 | K7: 12000 | L7: 16000 | M7: 4600 | N7: 3 | O7: 0.65 | P7: 0.75 | Q7: 16.068 | R7: 108.212 | S7: 70 | T7: 6500 | U7: 200
A8: Hai Phong | B8: haiphong.html | C8: Vietnam | D8: VN | E8: 800 | F8: 4 | G8: 26 | H8: 45 | I8: 0.1 | J8: 650 | K8: 10000 | L8: 15000 | M8: 3300 | N8: 3 | O8: 0.65 | P8: 0.75 | Q8: 20.865 | R8: 106.683 | S8: 72 | T8: 6500 | U8: 200
A9: Binh Duong | B9: binhduong.html | C9: Vietnam | D9: VN | E9: 800 | F9: 4 | G9: 26 | H9: 45 | I9: 0.1 | J9: 600 | K9: 10000 | L9: 14000 | M9: 3200 | N9: 3 | O9: 0.65 | P9: 0.75 | Q9: 10.98 | R9: 106.653 | S9: 75 | T9: 6500 | U9: 200
A10: Dong Nai | B10: dongnai.html | C10: Vietnam | D10: VN | E10: 800 | F10: 4 | G10: 26 | H10: 55 | I10: 0.1 | J10: 550 | K10: 9000 | L10: 13000 | M10: 3100 | N10: 3 | O10: 0.65 | P10: 0.75 | Q10: 10.945 | R10: 106.824 | S10: 73 | T10: 6500 | U10: 200
A11: Kuala Lumpur | B11: kuala_lumpur.html | C11: Malaysia | D11: MY | E11: 800 | F11: 3 | G11: 26 | H11: 90 | I11: 0.1 | J11: 3500 | K11: 33000 | L11: 20000 | M11: 6000 | N11: 3 | O11: 0.65 | P11: 0.75 | Q11: 3.148 | R11: 101.686 | S11: 40 | T11: 7500 | U11: 200
A12: Johor Bahru (RTS) | B12: johor.html | C12: Malaysia | D12: MY | E12: 1000 | F12: 4 | G12: 26 | H12: 65 | I12: 0.1 | J12: 1700 | K12: 28600 | L12: 18000 | M12: 5400 | N12: 3 | O12: 0.65 | P12: 0.75 | Q12: 1.492 | R12: 103.743 | S12: 55 | T12: 7500 | U12: 200
A13: Penang | B13: penang.html | C13: Malaysia | D13: MY | E13: 800 | F13: 4 | G13: 26 | H13: 55 | I13: 0.1 | J13: 800 | K13: 22000 | L13: 15000 | M13: 4800 | N13: 3 | O13: 0.65 | P13: 0.75 | Q13: 5.414 | R13: 100.33 | S13: 50 | T13: 7500 | U13: 200
A14: Sabah | B14: sabah.html | C14: Malaysia | D14: MY | E14: 800 | F14: 4 | G14: 26 | H14: 45 | I14: 0.1 | J14: 900 | K14: 19800 | L14: 14500 | M14: 4500 | N14: 3 | O14: 0.65 | P14: 0.75 | Q14: 5.978 | R14: 116.073 | S14: 75 | T14: 7500 | U14: 200
A15: Sarawak | B15: sarawak.html | C15: Malaysia | D15: MY | E15: 800 | F15: 4 | G15: 26 | H15: 46 | I15: 0.1 | J15: 700 | K15: 18700 | L15: 14000 | M15: 4200 | N15: 3 | O15: 0.65 | P15: 0.75 | Q15: 1.553 | R15: 110.36 | S15: 65 | T15: 7500 | U15: 200
A16: Singapore | B16: singapore.html | C16: Other APAC | D16: SG | E16: 750 | F16: 3 | G16: 26 | H16: 180 | I16: 0.1 | J16: 5500 | K16: 66600 | L16: 22000 | M16: 16500 | N16: 3 | O16: 0.65 | P16: 0.75 | Q16: 1.283 | R16: 103.85 | S16: 25 | T16: 4000 | U16: 300
... A31: Perth | B31: perth.html | C31: Australia | D31: AU | E31: 800 | F31: 3 | G31: 26 | H31: 200 | I31: 0.1 | J31: 2000 | K31: 74750 | L31: 19000 | M31: 6000 | N31: 3 | O31: 0.65 | P31: 0.75 | Q31: -31.953 | R31: 115.857 | S31: 38 | T31: 4500 | U31: 300

Sheet Model
A1: Oasis Salon — Calculated Financial Model (Auto-Generated from Cities Sheet)
A2: 🔒 Do not edit this sheet directly — change inputs in Cities sheet. BLUE = formula cells.
A3: IDENTITY | C3: SPACE & SEATS | F3: STAFFING MODEL | K3: COUNTRY RATES | P3: STAFF COST | Q3: MONTHLY OPEX | W3: CAPACITY | Z3: UNIT ECONOMICS | AC3: PROFIT & CASH FLOW | AG3: CAPEX & PAYBACK | AK3: RATIO | AL3: VIABLE?
A4: City Name | B4: Country | C4: Stations | D4: Color Bar Seats | E4: Total Seats | F4: Wash Basins | G4: Seniors | H4: Juniors | I4: Assistants | J4: Total Staff | K4: Tax Rate | L4: Senior (USD/mo) | M4: Junior (USD/mo) | N4: Assistant (USD/mo) | O4: Manager (USD/mo) | P4: Total Staff Cost (USD/mo) | Q4: Rent (USD/mo) | R4: Utilities (USD/mo) | S4: Mktg+Misc (USD/mo) | T4: Admin & SW (USD/mo) | U4: Monthly Deprec (USD) | V4: Total Cash OPEX (USD/mo) | W4: Max Capacity | X4: Y1 Clients (65%) | Y4: Y2 Clients (75%) | Z4: Breakeven (clients/mo) | AA4: COGS/session | AB4: GM/session (90%) | AC4: Y1 Monthly PAT (USD) | AD4: Y2 Monthly PAT (USD) | AE4: Y1 Monthly CashFlow (USD) | AF4: Y2 Monthly CashFlow (USD) | AG4: CAPEX Low | AH4: CAPEX High | AI4: CAPEX Mid | AJ4: Payback (months) | AK4: PAT/OPEX (%) | AL4: VIABLE? (BE < 80%cap)
A5: =Cities!A5 | B5: =Cities!D5 | C5: =IF(Cities!E5<=750,3,IF(Cities!E5<=850,4,5)) | D5: =C5-1 | E5: =C5+D5 | F5: =IF(C5<=4,2,3) | G5: =IF(C5<=4,2,3) | H5: =C5-G5 | I5: =CEILING(C5/2,1) | J5: =G5+H5+I5+1 | K5: =VLOOKUP(Cities!D5,Country!$A$4:$H$14,3,FALSE) | L5: =VLOOKUP(Cities!D5,Country!$A$4:$H$14,5,FALSE) | M5: =VLOOKUP(Cities!D5,Country!$A$4:$H$14,6,FALSE) | N5: =VLOOKUP(Cities!D5,Country!$A$4:$H$14,7,FALSE) | O5: =VLOOKUP(Cities!D5,Country!$A$4:$H$14,8,FALSE) | P5: =G5*L5+H5*M5+I5*N5+O5 | Q5: =Cities!J5 | R5: =200+C5*80 | S5: =350+C5*50+300+C5*30 | T5: =Cities!U5 | U5: =Cities!L5/60 | V5: =Q5+P5+R5+S5+T5 | W5: =C5*Cities!F5*Cities!G5 | X5: =INT(W5*Cities!O5) | Y5: =INT(W5*Cities!P5) | Z5: =CEILING((V5+U5)/AB5,1) | AA5: =Cities!H5*Cities!I5 | AB5: =Cities!H5-AA5 | AC5: =IF((X5*AB5-V5-U5)>0, (X5*AB5-V5-U5)*(1-K5), X5*AB5-V5-U5) | AD5: =IF((Y5*AB5-V5-U5)>0, (Y5*AB5-V5-U5)*(1-K5), Y5*AB5-V5-U5) | AE5: =AC5+U5 | AF5: =AD5+U5 | AG5: =FLOOR((Cities!K5+Cities!L5+Cities!M5+Cities!T5+Cities!J5*Cities!N5)*0.92,5000) | AH5: =CEILING((Cities!K5+Cities!L5+Cities!M5+Cities!T5+Cities!J5*Cities!N5)*1.08,5000) | AI5: =(AG5+AH5)/2 | AJ5: =IF(AE5*12>=AI5, IF(AE5>0,CEILING(AI5/AE5,1),999), IF(AF5>0,12+CEILING((AI5-AE5*12)/AF5,1),999)) | AK5: =IF(V5>0,AD5/V5,0) | AL5: =IF(Z5<W5*0.8,"✓ YES","⚠ TIGHT")
A6: =Cities!A6 | B6: =Cities!D6 | C6: =IF(Cities!E6<=750,3,IF(Cities!E6<=850,4,5)) | D6: =C6-1 | E6: =C6+D6 | F6: =IF(C6<=4,2,3) | G6: =IF(C6<=4,2,3) | H6: =C6-G6 | I6: =CEILING(C6/2,1) | J6: =G6+H6+I6+1 | K6: =VLOOKUP(Cities!D6,Country!$A$4:$H$14,3,FALSE) | L6: =VLOOKUP(Cities!D6,Country!$A$4:$H$14,5,FALSE) | M6: =VLOOKUP(Cities!D6,Country!$A$4:$H$14,6,FALSE) | N6: =VLOOKUP(Cities!D6,Country!$A$4:$H$14,7,FALSE) | O6: =VLOOKUP(Cities!D6,Country!$A$4:$H$14,8,FALSE) | P6: =G6*L6+H6*M6+I6*N6+O6 | Q6: =Cities!J6 | R6: =200+C6*80 | S6: =350+C6*50+300+C6*30 | T6: =Cities!U6 | U6: =Cities!L6/60 | V6: =Q6+P6+R6+S6+T6 | W6: =C6*Cities!F6*Cities!G6 | X6: =INT(W6*Cities!O6) | Y6: =INT(W6*Cities!P6) | Z6: =CEILING((V6+U6)/AB6,1) | AA6: =Cities!H6*Cities!I6 | AB6: =Cities!H6-AA6 | AC6: =IF((X6*AB6-V6-U6)>0, (X6*AB6-V6-U6)*(1-K6), X6*AB6-V6-U6) | AD6: =IF((Y6*AB6-V6-U6)>0, (Y6*AB6-V6-U6)*(1-K6), Y6*AB6-V6-U6) | AE6: =AC6+U6 | AF6: =AD6+U6 | AG6: =FLOOR((Cities!K6+Cities!L6+Cities!M6+Cities!T6+Cities!J6*Cities!N6)*0.92,5000) | AH6: =CEILING((Cities!K6+Cities!L6+Cities!M6+Cities!T6+Cities!J6*Cities!N6)*1.08,5000) | AI6: =(AG6+AH6)/2 | AJ6: =IF(AE6*12>=AI6, IF(AE6>0,CEILING(AI6/AE6,1),999), IF(AF6>0,12+CEILING((AI6-AE6*12)/AF6,1),999)) | AK6: =IF(V6>0,AD6/V6,0) | AL6: =IF(Z6<W6*0.8,"✓ YES","⚠ TIGHT")
A7: =Cities!A7 | B7: =Cities!D7 | C7: =IF(Cities!E7<=750,3,IF(Cities!E7<=850,4,5)) | D7: =C7-1 | E7: =C7+D7 | F7: =IF(C7<=4,2,3) | G7: =IF(C7<=4,2,3) | H7: =C7-G7 | I7: =CEILING(C7/2,1) | J7: =G7+H7+I7+1 | K7: =VLOOKUP(Cities!D7,Country!$A$4:$H$14,3,FALSE) | L7: =VLOOKUP(Cities!D7,Country!$A$4:$H$14,5,FALSE) | M7: =VLOOKUP(Cities!D7,Country!$A$4:$H$14,6,FALSE) | N7: =VLOOKUP(Cities!D7,Country!$A$4:$H$14,7,FALSE) | O7: =VLOOKUP(Cities!D7,Country!$A$4:$H$14,8,FALSE) | P7: =G7*L7+H7*M7+I7*N7+O7 | Q7: =Cities!J7 | R7: =200+C7*80 | S7: =350+C7*50+300+C7*30 | T7: =Cities!U7 | U7: =Cities!L7/60 | V7: =Q7+P7+R7+S7+T7 | W7: =C7*Cities!F7*Cities!G7 | X7: =INT(W7*Cities!O7) | Y7: =INT(W7*Cities!P7) | Z7: =CEILING((V7+U7)/AB7,1) | AA7: =Cities!H7*Cities!I7 | AB7: =Cities!H7-AA7 | AC7: =IF((X7*AB7-V7-U7)>0, (X7*AB7-V7-U7)*(1-K7), X7*AB7-V7-U7) | AD7: =IF((Y7*AB7-V7-U7)>0, (Y7*AB7-V7-U7)*(1-K7), Y7*AB7-V7-U7) | AE7: =AC7+U7 | AF7: =AD7+U7 | AG7: =FLOOR((Cities!K7+Cities!L7+Cities!M7+Cities!T7+Cities!J7*Cities!N7)*0.92,5000) | AH7: =CEILING((Cities!K7+Cities!L7+Cities!M7+Cities!T7+Cities!J7*Cities!N7)*1.08,5000) | AI7: =(AG7+AH7)/2 | AJ7: =IF(AE7*12>=AI7, IF(AE7>0,CEILING(AI7/AE7,1),999), IF(AF7>0,12+CEILING((AI7-AE7*12)/AF7,1),999)) | AK7: =IF(V7>0,AD7/V7,0) | AL7: =IF(Z7<W7*0.8,"✓ YES","⚠ TIGHT")
A8: =Cities!A8 | B8: =Cities!D8 | C8: =IF(Cities!E8<=750,3,IF(Cities!E8<=850,4,5)) | D8: =C8-1 | E8: =C8+D8 | F8: =IF(C8<=4,2,3) | G8: =IF(C8<=4,2,3) | H8: =C8-G8 | I8: =CEILING(C8/2,1) | J8: =G8+H8+I8+1 | K8: =VLOOKUP(Cities!D8,Country!$A$4:$H$14,3,FALSE) | L8: =VLOOKUP(Cities!D8,Country!$A$4:$H$14,5,FALSE) | M8: =VLOOKUP(Cities!D8,Country!$A$4:$H$14,6,FALSE) | N8: =VLOOKUP(Cities!D8,Country!$A$4:$H$14,7,FALSE) | O8: =VLOOKUP(Cities!D8,Country!$A$4:$H$14,8,FALSE) | P8: =G8*L8+H8*M8+I8*N8+O8 | Q8: =Cities!J8 | R8: =200+C8*80 | S8: =350+C8*50+300+C8*30 | T8: =Cities!U8 | U8: =Cities!L8/60 | V8: =Q8+P8+R8+S8+T8 | W8: =C8*Cities!F8*Cities!G8 | X8: =INT(W8*Cities!O8) | Y8: =INT(W8*Cities!P8) | Z8: =CEILING((V8+U8)/AB8,1) | AA8: =Cities!H8*Cities!I8 | AB8: =Cities!H8-AA8 | AC8: =IF((X8*AB8-V8-U8)>0, (X8*AB8-V8-U8)*(1-K8), X8*AB8-V8-U8) | AD8: =IF((Y8*AB8-V8-U8)>0, (Y8*AB8-V8-U8)*(1-K8), Y8*AB8-V8-U8) | AE8: =AC8+U8 | AF8: =AD8+U8 | AG8: =FLOOR((Cities!K8+Cities!L8+Cities!M8+Cities!T8+Cities!J8*Cities!N8)*0.92,5000) | AH8: =CEILING((Cities!K8+Cities!L8+Cities!M8+Cities!T8+Cities!J8*Cities!N8)*1.08,5000) | AI8: =(AG8+AH8)/2 | AJ8: =IF(AE8*12>=AI8, IF(AE8>0,CEILING(AI8/AE8,1),999), IF(AF8>0,12+CEILING((AI8-AE8*12)/AF8,1),999)) | AK8: =IF(V8>0,AD8/V8,0) | AL8: =IF(Z8<W8*0.8,"✓ YES","⚠ TIGHT")
A9: =Cities!A9 | B9: =Cities!D9 | C9: =IF(Cities!E9<=750,3,IF(Cities!E9<=850,4,5)) | D9: =C9-1 | E9: =C9+D9 | F9: =IF(C9<=4,2,3) | G9: =IF(C9<=4,2,3) | H9: =C9-G9 | I9: =CEILING(C9/2,1) | J9: =G9+H9+I9+1 | K9: =VLOOKUP(Cities!D9,Country!$A$4:$H$14,3,FALSE) | L9: =VLOOKUP(Cities!D9,Country!$A$4:$H$14,5,FALSE) | M9: =VLOOKUP(Cities!D9,Country!$A$4:$H$14,6,FALSE) | N9: =VLOOKUP(Cities!D9,Country!$A$4:$H$14,7,FALSE) | O9: =VLOOKUP(Cities!D9,Country!$A$4:$H$14,8,FALSE) | P9: =G9*L9+H9*M9+I9*N9+O9 | Q9: =Cities!J9 | R9: =200+C9*80 | S9: =350+C9*50+300+C9*30 | T9: =Cities!U9 | U9: =Cities!L9/60 | V9: =Q9+P9+R9+S9+T9 | W9: =C9*Cities!F9*Cities!G9 | X9: =INT(W9*Cities!O9) | Y9: =INT(W9*Cities!P9) | Z9: =CEILING((V9+U9)/AB9,1) | AA9: =Cities!H9*Cities!I9 | AB9: =Cities!H9-AA9 | AC9: =IF((X9*AB9-V9-U9)>0, (X9*AB9-V9-U9)*(1-K9), X9*AB9-V9-U9) | AD9: =IF((Y9*AB9-V9-U9)>0, (Y9*AB9-V9-U9)*(1-K9), Y9*AB9-V9-U9) | AE9: =AC9+U9 | AF9: =AD9+U9 | AG9: =FLOOR((Cities!K9+Cities!L9+Cities!M9+Cities!T9+Cities!J9*Cities!N9)*0.92,5000) | AH9: =CEILING((Cities!K9+Cities!L9+Cities!M9+Cities!T9+Cities!J9*Cities!N9)*1.08,5000) | AI9: =(AG9+AH9)/2 | AJ9: =IF(AE9*12>=AI9, IF(AE9>0,CEILING(AI9/AE9,1),999), IF(AF9>0,12+CEILING((AI9-AE9*12)/AF9,1),999)) | AK9: =IF(V9>0,AD9/V9,0) | AL9: =IF(Z9<W9*0.8,"✓ YES","⚠ TIGHT")
A10: =Cities!A10 | B10: =Cities!D10 | C10: =IF(Cities!E10<=750,3,IF(Cities!E10<=850,4,5)) | D10: =C10-1 | E10: =C10+D10 | F10: =IF(C10<=4,2,3) | G10: =IF(C10<=4,2,3) | H10: =C10-G10 | I10: =CEILING(C10/2,1) | J10: =G10+H10+I10+1 | K10: =VLOOKUP(Cities!D10,Country!$A$4:$H$14,3,FALSE) | L10: =VLOOKUP(Cities!D10,Country!$A$4:$H$14,5,FALSE) | M10: =VLOOKUP(Cities!D10,Country!$A$4:$H$14,6,FALSE) | N10: =VLOOKUP(Cities!D10,Country!$A$4:$H$14,7,FALSE) | O10: =VLOOKUP(Cities!D10,Country!$A$4:$H$14,8,FALSE) | P10: =G10*L10+H10*M10+I10*N10+O10 | Q10: =Cities!J10 | R10: =200+C10*80 | S10: =350+C10*50+300+C10*30 | T10: =Cities!U10 | U10: =Cities!L10/60 | V10: =Q10+P10+R10+S10+T10 | W10: =C10*Cities!F10*Cities!G10 | X10: =INT(W10*Cities!O10) | Y10: =INT(W10*Cities!P10) | Z10: =CEILING((V10+U10)/AB10,1) | AA10: =Cities!H10*Cities!I10 | AB10: =Cities!H10-AA10 | AC10: =IF((X10*AB10-V10-U10)>0, (X10*AB10-V10-U10)*(1-K10), X10*AB10-V10-U10) | AD10: =IF((Y10*AB10-V10-U10)>0, (Y10*AB10-V10-U10)*(1-K10), Y10*AB10-V10-U10) | AE10: =AC10+U10 | AF10: =AD10+U10 | AG10: =FLOOR((Cities!K10+Cities!L10+Cities!M10+Cities!T10+Cities!J10*Cities!N10)*0.92,5000) | AH10: =CEILING((Cities!K10+Cities!L10+Cities!M10+Cities!T10+Cities!J10*Cities!N10)*1.08,5000) | AI10: =(AG10+AH10)/2 | AJ10: =IF(AE10*12>=AI10, IF(AE10>0,CEILING(AI10/AE10,1),999), IF(AF10>0,12+CEILING((AI10-AE10*12)/AF10,1),999)) | AK10: =IF(V10>0,AD10/V10,0) | AL10: =IF(Z10<W10*0.8,"✓ YES","⚠ TIGHT")
A11: =Cities!A11 | B11: =Cities!D11 | C11: =IF(Cities!E11<=750,3,IF(Cities!E11<=850,4,5)) | D11: =C11-1 | E11: =C11+D11 | F11: =IF(C11<=4,2,3) | G11: =IF(C11<=4,2,3) | H11: =C11-G11 | I11: =CEILING(C11/2,1) | J11: =G11+H11+I11+1 | K11: =VLOOKUP(Cities!D11,Country!$A$4:$H$14,3,FALSE) | L11: =VLOOKUP(Cities!D11,Country!$A$4:$H$14,5,FALSE) | M11: =VLOOKUP(Cities!D11,Country!$A$4:$H$14,6,FALSE) | N11: =VLOOKUP(Cities!D11,Country!$A$4:$H$14,7,FALSE) | O11: =VLOOKUP(Cities!D11,Country!$A$4:$H$14,8,FALSE) | P11: =G11*L11+H11*M11+I11*N11+O11 | Q11: =Cities!J11 | R11: =200+C11*80 | S11: =350+C11*50+300+C11*30 | T11: =Cities!U11 | U11: =Cities!L11/60 | V11: =Q11+P11+R11+S11+T11 | W11: =C11*Cities!F11*Cities!G11 | X11: =INT(W11*Cities!O11) | Y11: =INT(W11*Cities!P11) | Z11: =CEILING((V11+U11)/AB11,1) | AA11: =Cities!H11*Cities!I11 | AB11: =Cities!H11-AA11 | AC11: =IF((X11*AB11-V11-U11)>0, (X11*AB11-V11-U11)*(1-K11), X11*AB11-V11-U11) | AD11: =IF((Y11*AB11-V11-U11)>0, (Y11*AB11-V11-U11)*(1-K11), Y11*AB11-V11-U11) | AE11: =AC11+U11 | AF11: =AD11+U11 | AG11: =FLOOR((Cities!K11+Cities!L11+Cities!M11+Cities!T11+Cities!J11*Cities!N11)*0.92,5000) | AH11: =CEILING((Cities!K11+Cities!L11+Cities!M11+Cities!T11+Cities!J11*Cities!N11)*1.08,5000) | AI11: =(AG11+AH11)/2 | AJ11: =IF(AE11*12>=AI11, IF(AE11>0,CEILING(AI11/AE11,1),999), IF(AF11>0,12+CEILING((AI11-AE11*12)/AF11,1),999)) | AK11: =IF(V11>0,AD11/V11,0) | AL11: =IF(Z11<W11*0.8,"✓ YES","⚠ TIGHT")
A12: =Cities!A12 | B12: =Cities!D12 | C12: =IF(Cities!E12<=750,3,IF(Cities!E12<=850,4,5)) | D12: =C12-1 | E12: =C12+D12 | F12: =IF(C12<=4,2,3) | G12: =IF(C12<=4,2,3) | H12: =C12-G12 | I12: =CEILING(C12/2,1) | J12: =G12+H12+I12+1 | K12: =VLOOKUP(Cities!D12,Country!$A$4:$H$14,3,FALSE) | L12: =VLOOKUP(Cities!D12,Country!$A$4:$H$14,5,FALSE) | M12: =VLOOKUP(Cities!D12,Country!$A$4:$H$14,6,FALSE) | N12: =VLOOKUP(Cities!D12,Country!$A$4:$H$14,7,FALSE) | O12: =VLOOKUP(Cities!D12,Country!$A$4:$H$14,8,FALSE) | P12: =G12*L12+H12*M12+I12*N12+O12 | Q12: =Cities!J12 | R12: =200+C12*80 | S12: =350+C12*50+300+C12*30 | T12: =Cities!U12 | U12: =Cities!L12/60 | V12: =Q12+P12+R12+S12+T12 | W12: =C12*Cities!F12*Cities!G12 | X12: =INT(W12*Cities!O12) | Y12: =INT(W12*Cities!P12) | Z12: =CEILING((V12+U12)/AB12,1) | AA12: =Cities!H12*Cities!I12 | AB12: =Cities!H12-AA12 | AC12: =IF((X12*AB12-V12-U12)>0, (X12*AB12-V12-U12)*(1-K12), X12*AB12-V12-U12) | AD12: =IF((Y12*AB12-V12-U12)>0, (Y12*AB12-V12-U12)*(1-K12), Y12*AB12-V12-U12) | AE12: =AC12+U12 | AF12: =AD12+U12 | AG12: =FLOOR((Cities!K12+Cities!L12+Cities!M12+Cities!T12+Cities!J12*Cities!N12)*0.92,5000) | AH12: =CEILING((Cities!K12+Cities!L12+Cities!M12+Cities!T12+Cities!J12*Cities!N12)*1.08,5000) | AI12: =(AG12+AH12)/2 | AJ12: =IF(AE12*12>=AI12, IF(AE12>0,CEILING(AI12/AE12,1),999), IF(AF12>0,12+CEILING((AI12-AE12*12)/AF12,1),999)) | AK12: =IF(V12>0,AD12/V12,0) | AL12: =IF(Z12<W12*0.8,"✓ YES","⚠ TIGHT")
A13: =Cities!A13 | B13: =Cities!D13 | C13: =IF(Cities!E13<=750,3,IF(Cities!E13<=850,4,5)) | D13: =C13-1 | E13: =C13+D13 | F13: =IF(C13<=4,2,3) | G13: =IF(C13<=4,2,3) | H13: =C13-G13 | I13: =CEILING(C13/2,1) | J13: =G13+H13+I13+1 | K13: =VLOOKUP(Cities!D13,Country!$A$4:$H$14,3,FALSE) | L13: =VLOOKUP(Cities!D13,Country!$A$4:$H$14,5,FALSE) | M13: =VLOOKUP(Cities!D13,Country!$A$4:$H$14,6,FALSE) | N13: =VLOOKUP(Cities!D13,Country!$A$4:$H$14,7,FALSE) | O13: =VLOOKUP(Cities!D13,Country!$A$4:$H$14,8,FALSE) | P13: =G13*L13+H13*M13+I13*N13+O13 | Q13: =Cities!J13 | R13: =200+C13*80 | S13: =350+C13*50+300+C13*30 | T13: =Cities!U13 | U13: =Cities!L13/60 | V13: =Q13+P13+R13+S13+T13 | W13: =C13*Cities!F13*Cities!G13 | X13: =INT(W13*Cities!O13) | Y13: =INT(W13*Cities!P13) | Z13: =CEILING((V13+U13)/AB13,1) | AA13: =Cities!H13*Cities!I13 | AB13: =Cities!H13-AA13 | AC13: =IF((X13*AB13-V13-U13)>0, (X13*AB13-V13-U13)*(1-K13), X13*AB13-V13-U13) | AD13: =IF((Y13*AB13-V13-U13)>0, (Y13*AB13-V13-U13)*(1-K13), Y13*AB13-V13-U13) | AE13: =AC13+U13 | AF13: =AD13+U13 | AG13: =FLOOR((Cities!K13+Cities!L13+Cities!M13+Cities!T13+Cities!J13*Cities!N13)*0.92,5000) | AH13: =CEILING((Cities!K13+Cities!L13+Cities!M13+Cities!T13+Cities!J13*Cities!N13)*1.08,5000) | AI13: =(AG13+AH13)/2 | AJ13: =IF(AE13*12>=AI13, IF(AE13>0,CEILING(AI13/AE13,1),999), IF(AF13>0,12+CEILING((AI13-AE13*12)/AF13,1),999)) | AK13: =IF(V13>0,AD13/V13,0) | AL13: =IF(Z13<W13*0.8,"✓ YES","⚠ TIGHT")
A14: =Cities!A14 | B14: =Cities!D14 | C14: =IF(Cities!E14<=750,3,IF(Cities!E14<=850,4,5)) | D14: =C14-1 | E14: =C14+D14 | F14: =IF(C14<=4,2,3) | G14: =IF(C14<=4,2,3) | H14: =C14-G14 | I14: =CEILING(C14/2,1) | J14: =G14+H14+I14+1 | K14: =VLOOKUP(Cities!D14,Country!$A$4:$H$14,3,FALSE) | L14: =VLOOKUP(Cities!D14,Country!$A$4:$H$14,5,FALSE) | M14: =VLOOKUP(Cities!D14,Country!$A$4:$H$14,6,FALSE) | N14: =VLOOKUP(Cities!D14,Country!$A$4:$H$14,7,FALSE) | O14: =VLOOKUP(Cities!D14,Country!$A$4:$H$14,8,FALSE) | P14: =G14*L14+H14*M14+I14*N14+O14 | Q14: =Cities!J14 | R14: =200+C14*80 | S14: =350+C14*50+300+C14*30 | T14: =Cities!U14 | U14: =Cities!L14/60 | V14: =Q14+P14+R14+S14+T14 | W14: =C14*Cities!F14*Cities!G14 | X14: =INT(W14*Cities!O14) | Y14: =INT(W14*Cities!P14) | Z14: =CEILING((V14+U14)/AB14,1) | AA14: =Cities!H14*Cities!I14 | AB14: =Cities!H14-AA14 | AC14: =IF((X14*AB14-V14-U14)>0, (X14*AB14-V14-U14)*(1-K14), X14*AB14-V14-U14) | AD14: =IF((Y14*AB14-V14-U14)>0, (Y14*AB14-V14-U14)*(1-K14), Y14*AB14-V14-U14) | AE14: =AC14+U14 | AF14: =AD14+U14 | AG14: =FLOOR((Cities!K14+Cities!L14+Cities!M14+Cities!T14+Cities!J14*Cities!N14)*0.92,5000) | AH14: =CEILING((Cities!K14+Cities!L14+Cities!M14+Cities!T14+Cities!J14*Cities!N14)*1.08,5000) | AI14: =(AG14+AH14)/2 | AJ14: =IF(AE14*12>=AI14, IF(AE14>0,CEILING(AI14/AE14,1),999), IF(AF14>0,12+CEILING((AI14-AE14*12)/AF14,1),999)) | AK14: =IF(V14>0,AD14/V14,0) | AL14: =IF(Z14<W14*0.8,"✓ YES","⚠ TIGHT")
A15: =Cities!A15 | B15: =Cities!D15 | C15: =IF(Cities!E15<=750,3,IF(Cities!E15<=850,4,5)) | D15: =C15-1 | E15: =C15+D15 | F15: =IF(C15<=4,2,3) | G15: =IF(C15<=4,2,3) | H15: =C15-G15 | I15: =CEILING(C15/2,1) | J15: =G15+H15+I15+1 | K15: =VLOOKUP(Cities!D15,Country!$A$4:$H$14,3,FALSE) | L15: =VLOOKUP(Cities!D15,Country!$A$4:$H$14,5,FALSE) | M15: =VLOOKUP(Cities!D15,Country!$A$4:$H$14,6,FALSE) | N15: =VLOOKUP(Cities!D15,Country!$A$4:$H$14,7,FALSE) | O15: =VLOOKUP(Cities!D15,Country!$A$4:$H$14,8,FALSE) | P15: =G15*L15+H15*M15+I15*N15+O15 | Q15: =Cities!J15 | R15: =200+C15*80 | S15: =350+C15*50+300+C15*30 | T15: =Cities!U15 | U15: =Cities!L15/60 | V15: =Q15+P15+R15+S15+T15 | W15: =C15*Cities!F15*Cities!G15 | X15: =INT(W15*Cities!O15) | Y15: =INT(W15*Cities!P15) | Z15: =CEILING((V15+U15)/AB15,1) | AA15: =Cities!H15*Cities!I15 | AB15: =Cities!H15-AA15 | AC15: =IF((X15*AB15-V15-U15)>0, (X15*AB15-V15-U15)*(1-K15), X15*AB15-V15-U15) | AD15: =IF((Y15*AB15-V15-U15)>0, (Y15*AB15-V15-U15)*(1-K15), Y15*AB15-V15-U15) | AE15: =AC15+U15 | AF15: =AD15+U15 | AG15: =FLOOR((Cities!K15+Cities!L15+Cities!M15+Cities!T15+Cities!J15*Cities!N15)*0.92,5000) | AH15: =CEILING((Cities!K15+Cities!L15+Cities!M15+Cities!T15+Cities!J15*Cities!N15)*1.08,5000) | AI15: =(AG15+AH15)/2 | AJ15: =IF(AE15*12>=AI15, IF(AE15>0,CEILING(AI15/AE15,1),999), IF(AF15>0,12+CEILING((AI15-AE15*12)/AF15,1),999)) | AK15: =IF(V15>0,AD15/V15,0) | AL15: =IF(Z15<W15*0.8,"✓ YES","⚠ TIGHT")
A16: =Cities!A16 | B16: =Cities!D16 | C16: =IF(Cities!E16<=750,3,IF(Cities!E16<=850,4,5)) | D16: =C16-1 | E16: =C16+D16 | F16: =IF(C16<=4,2,3) | G16: =IF(C16<=4,2,3) | H16: =C16-G16 | I16: =CEILING(C16/2,1) | J16: =G16+H16+I16+1 | K16: =VLOOKUP(Cities!D16,Country!$A$4:$H$14,3,FALSE) | L16: =VLOOKUP(Cities!D16,Country!$A$4:$H$14,5,FALSE) | M16: =VLOOKUP(Cities!D16,Country!$A$4:$H$14,6,FALSE) | N16: =VLOOKUP(Cities!D16,Country!$A$4:$H$14,7,FALSE) | O16: =VLOOKUP(Cities!D16,Country!$A$4:$H$14,8,FALSE) | P16: =G16*L16+H16*M16+I16*N16+O16 | Q16: =Cities!J16 | R16: =200+C16*80 | S16: =350+C16*50+300+C16*30 | T16: =Cities!U16 | U16: =Cities!L16/60 | V16: =Q16+P16+R16+S16+T16 | W16: =C16*Cities!F16*Cities!G16 | X16: =INT(W16*Cities!O16) | Y16: =INT(W16*Cities!P16) | Z16: =CEILING((V16+U16)/AB16,1) | AA16: =Cities!H16*Cities!I16 | AB16: =Cities!H16-AA16 | AC16: =IF((X16*AB16-V16-U16)>0, (X16*AB16-V16-U16)*(1-K16), X16*AB16-V16-U16) | AD16: =IF((Y16*AB16-V16-U16)>0, (Y16*AB16-V16-U16)*(1-K16), Y16*AB16-V16-U16) | AE16: =AC16+U16 | AF16: =AD16+U16 | AG16: =FLOOR((Cities!K16+Cities!L16+Cities!M16+Cities!T16+Cities!J16*Cities!N16)*0.92,5000) | AH16: =CEILING((Cities!K16+Cities!L16+Cities!M16+Cities!T16+Cities!J16*Cities!N16)*1.08,5000) | AI16: =(AG16+AH16)/2 | AJ16: =IF(AE16*12>=AI16, IF(AE16>0,CEILING(AI16/AE16,1),999), IF(AF16>0,12+CEILING((AI16-AE16*12)/AF16,1),999)) | AK16: =IF(V16>0,AD16/V16,0) | AL16: =IF(Z16<W16*0.8,"✓ YES","⚠ TIGHT")
... A31: =Cities!A31 | B31: =Cities!D31 | C31: =IF(Cities!E31<=750,3,IF(Cities!E31<=850,4,5)) | D31: =C31-1 | E31: =C31+D31 | F31: =IF(C31<=4,2,3) | G31: =IF(C31<=4,2,3) | H31: =C31-G31 | I31: =CEILING(C31/2,1) | J31: =G31+H31+I31+1 | K31: =VLOOKUP(Cities!D31,Country!$A$4:$H$14,3,FALSE) | L31: =VLOOKUP(Cities!D31,Country!$A$4:$H$14,5,FALSE) | M31: =VLOOKUP(Cities!D31,Country!$A$4:$H$14,6,FALSE) | N31: =VLOOKUP(Cities!D31,Country!$A$4:$H$14,7,FALSE) | O31: =VLOOKUP(Cities!D31,Country!$A$4:$H$14,8,FALSE) | P31: =G31*L31+H31*M31+I31*N31+O31 | Q31: =Cities!J31 | R31: =200+C31*80 | S31: =350+C31*50+300+C31*30 | T31: =Cities!U31 | U31: =Cities!L31/60 | V31: =Q31+P31+R31+S31+T31 | W31: =C31*Cities!F31*Cities!G31 | X31: =INT(W31*Cities!O31) | Y31: =INT(W31*Cities!P31) | Z31: =CEILING((V31+U31)/AB31,1) | AA31: =Cities!H31*Cities!I31 | AB31: =Cities!H31-AA31 | AC31: =IF((X31*AB31-V31-U31)>0, (X31*AB31-V31-U31)*(1-K31), X31*AB31-V31-U31) | AD31: =IF((Y31*AB31-V31-U31)>0, (Y31*AB31-V31-U31)*(1-K31), Y31*AB31-V31-U31) | AE31: =AC31+U31 | AF31: =AD31+U31 | AG31: =FLOOR((Cities!K31+Cities!L31+Cities!M31+Cities!T31+Cities!J31*Cities!N31)*0.92,5000) | AH31: =CEILING((Cities!K31+Cities!L31+Cities!M31+Cities!T31+Cities!J31*Cities!N31)*1.08,5000) | AI31: =(AG31+AH31)/2 | AJ31: =IF(AE31*12>=AI31, IF(AE31>0,CEILING(AI31/AE31,1),999), IF(AF31>0,12+CEILING((AI31-AE31*12)/AF31,1),999)) | AK31: =IF(V31>0,AD31/V31,0) | AL31: =IF(Z31<W31*0.8,"✓ YES","⚠ TIGHT")

Sheet CAPEX_Details
A1: City | B1: Category | C1: Component | D1: Cost_USD | E1: Reference
A2: Ho Chi Minh | B2: Fitout | C2: Interior Renovation & Drywall Partitioning | D2: 8000 | E2: Local contractor labor and material cost estimates
A3: Ho Chi Minh | B3: Fitout | C3: Custom Joinery (Vanity units, retail shelving) | D3: 6000 | E3: Custom carpenter fabrication quotes for salon styling stations
A4: Ho Chi Minh | B4: Fitout | C4: Lighting & Electrical Installations (High-CRI) | D4: 3000 | E4: Track lighting, wiring, and power outlet distribution quotes
A5: Ho Chi Minh | B5: Fitout | C5: Flooring & Ceiling Works | D5: 3000 | E5: Acoustic ceiling tiling and water-resistant wood/tile flooring quotes
A6: Ho Chi Minh | B6: Equipment | C6: Takara Belmont Styling Chairs (4 units) | D6: 8000 | E6: Takara Belmont B2B Pricing Catalog (Premium Series)
A7: Ho Chi Minh | B7: Equipment | C7: Takara Belmont Backwash Wash Basins (2 units) | D7: 7000 | E7: Takara Belmont Wash Systems Catalog 2025
A8: Ho Chi Minh | B8: Equipment | C8: Water Softening & Multi-Stage Filtration System | D8: 5000 | E8: Commercial RO system specifications and installation quote
A9: Ho Chi Minh | B9: Other CAPEX | C9: Initial Color & Chemical Inventory (Stock) | D9: 4500 | E9: Wella Professionals & Milbon Distributor Starter Stock list
A10: Ho Chi Minh | B10: Other CAPEX | C10: Professional Styling Tools (Dyson dryers, shears) | D10: 2250 | E10: Dyson Professional Partner Pricing & shears kit catalog
A11: Ho Chi Minh | B11: Other CAPEX | C11: Retail Product Initial Stock (Oribe, Kérastase) | D11: 2250 | E11: Oribe & Kérastase B2B opening inventory order guidelines
A12: Ho Chi Minh | B12: Deposit | C12: Commercial Landlord Security Deposit (3 months) | D12: 9000 | E12: Standard commercial landlord lease terms for prime retail
A13: Ho Chi Minh | B13: Biz Reg | C13: Company Incorporation & Legal Registrations | D13: 3900 | E13: Local Companies Registry & foreign entity setup filing fees
... A352: Perth | B352: Biz Reg | C352: Annual Resident Agent & Secretary Retainer | D352: 1800 | E352: Local corporate services provider standard annual pricing

Sheet OPEX_Details
A1: City | B1: Category | C1: Component | D1: Cost_USD | E1: Reference
A2: Ho Chi Minh | B2: Rent | C2: Base Commercial Rent (inc. service charges) | D2: 3000 | E2: Estimated prime retail rental rates for recommended locations
A3: Ho Chi Minh | B3: Staff Cost | C3: Senior Hair Stylist Salary (2 headcount) | D3: 1600 | E3: National Hairdresser Salary Survey for Senior Stylists (Base of $800.0/mo)
A4: Ho Chi Minh | B4: Staff Cost | C4: Junior Hair Stylist Salary (2 headcount) | D4: 1000 | E4: National Hairdresser Salary Survey for Junior Stylists (Base of $500.0/mo)
A5: Ho Chi Minh | B5: Staff Cost | C5: Stylist Assistants / Techs (2 headcount) | D5: 840 | E5: National Hairdresser Salary Survey for Assistants (Base of $420.0/mo)
A6: Ho Chi Minh | B6: Staff Cost | C6: Salon Manager / Receptionist Salary (1 headcount) | D6: 1100 | E6: National Salary Survey for Salon Managers (Base of $1100.0/mo)
A7: Ho Chi Minh | B7: Utilities | C7: Electricity (AC, blowdryers, lighting) | D7: 312 | E7: Local electric power utility commercial tariff estimates
A8: Ho Chi Minh | B8: Utilities | C8: Water & Filtration Replacement Filters | D8: 208 | E8: Local water utility charges and recurring demineralizer filters cost
A9: Ho Chi Minh | B9: Marketing & Misc | C9: Localized Social Media Advertising (Meta, IG) | D9: 582 | E9: Local Facebook & Instagram targeted advertising agency packages
A10: Ho Chi Minh | B10: Marketing & Misc | C10: PR, Influencer (KOL) Invites & Print Material | D10: 388 | E10: Launch month promotion campaign and graphic design print materials
A11: Ho Chi Minh | B11: Admin & SW | C11: Salon Booking Software & POS SaaS Subscription | D11: 80 | E11: Phorest POS software monthly subscription charges for 4-5 stations
A12: Ho Chi Minh | B12: Admin & SW | C12: Commercial Insurance, Bookkeeping & Compliance | D12: 120 | E12: Local business insurance quote & independent accountant retainer
A13: Hanoi | B13: Rent | C13: Base Commercial Rent (inc. service charges) | D13: 2200 | E13: Estimated prime retail rental rates for recommended locations
... A298: Perth | B298: Admin & SW | C298: Commercial Insurance, Bookkeeping & Compliance | D298: 180 | E298: Local business insurance quote & independent accountant retainer
